{
  "statistics": {
    "num_features": 100,
    "mean_loss_diff": -0.183721923828125,
    "median_loss_diff": -0.08636474609375,
    "std_loss_diff": 0.5741468463370654,
    "max_loss_diff": 1.604248046875,
    "mean_relative_importance": -0.0002670699732873459,
    "median_relative_importance": -0.00012554533477346082
  },
  "top_10_by_loss_diff": [
    {
      "feature_id": 71,
      "loss_diff": 1.604248046875,
      "relative_importance": 0.0023320378651488652
    },
    {
      "feature_id": 80,
      "loss_diff": 1.0650634765625,
      "relative_importance": 0.001548244587842326
    },
    {
      "feature_id": 10,
      "loss_diff": 0.72418212890625,
      "relative_importance": 0.0010527175951145673
    },
    {
      "feature_id": 34,
      "loss_diff": 0.70733642578125,
      "relative_importance": 0.0010282296004873763
    },
    {
      "feature_id": 7,
      "loss_diff": 0.60107421875,
      "relative_importance": 0.0008737600401760015
    },
    {
      "feature_id": 69,
      "loss_diff": 0.51824951171875,
      "relative_importance": 0.0007533607332589794
    },
    {
      "feature_id": 22,
      "loss_diff": 0.50140380859375,
      "relative_importance": 0.0007288727386317884
    },
    {
      "feature_id": 43,
      "loss_diff": 0.4560546875,
      "relative_importance": 0.0006629503472984447
    },
    {
      "feature_id": 12,
      "loss_diff": 0.42828369140625,
      "relative_importance": 0.0006225806460108654
    },
    {
      "feature_id": 56,
      "loss_diff": 0.39288330078125,
      "relative_importance": 0.0005711203674464787
    }
  ]
}